app/__init__.py
app/main.py
app/models.py
calculator_lib/__init__.py
calculator_lib/operations.py
test_lib/__init__.py
test_lib/test_lib_main.py
tests/__init__.py
tests/test_main.py
calculator_lib_brunoowcx-0.1.1.dist-info/METADATA
calculator_lib_brunoowcx-0.1.1.dist-info/WHEEL
calculator_lib_brunoowcx-0.1.1.dist-info/top_level.txt
calculator_lib_brunoowcx-0.1.1.dist-info/RECORD
