Metadata-Version: 2.4
Name: calculator-lib-brunoowcx
Version: 0.1.1
Summary: Biblioteca de operações matemáticas básicas em Python com raiz e exponencial.
Home-page: https://github.com/brunoowcx/calculadora-fastapi-lib
Author: Bruno Alves de Moraes
Author-email: Bruno Alves de Moraes <brunowcxl@gmail.com>
Project-URL: Homepage, https://github.com/brunowcx/calculadora-fastapi-lib
Classifier: Programming Language :: Python :: 3
Classifier: License :: OSI Approved :: MIT License
Classifier: Operating System :: OS Independent
Requires-Python: >=3.8
Dynamic: author
Dynamic: home-page
Dynamic: requires-python
